osrm/__init__.py
osrm/client_async.py
osrm/client_sync.py
osrm/model.py
osrm/utils.py
py_osrm_client-1.2.0.dist-info/licenses/LICENSE
py_osrm_client-1.2.0.dist-info/METADATA
py_osrm_client-1.2.0.dist-info/WHEEL
py_osrm_client-1.2.0.dist-info/top_level.txt
py_osrm_client-1.2.0.dist-info/RECORD
