Metadata-Version: 2.4
Name: py-osrm-client
Version: 1.2.0
Summary: Python client for OSRM api
Author-email: Tommaso Rossi <tommaso.rossi1@protonmail.com>
License: MIT
Project-URL: Homepage, https://github.com/tomrss/py-osrm-client
Project-URL: Issues, https://github.com/tomrss/py-osrm-client/issues
Keywords: osrm,osrm-api,client
Classifier: Development Status :: 4 - Beta
Classifier: License :: OSI Approved :: MIT License
Classifier: Operating System :: POSIX
Classifier: Programming Language :: Python :: 3
Classifier: Programming Language :: Python :: 3.8
Classifier: Programming Language :: Python :: 3.9
Classifier: Programming Language :: Python :: 3.10
Classifier: Programming Language :: Python :: 3.11
Classifier: Topic :: Software Development :: Libraries
Classifier: Topic :: Software Development :: Libraries :: Python Modules
Requires-Python: >=3.8
License-File: LICENSE
Requires-Dist: aiohttp>=3.7.0
Requires-Dist: requests>=2.0.0
Provides-Extra: tests
Requires-Dist: pytest>7.4; extra == "tests"
Requires-Dist: pytest-asyncio>0.23; extra == "tests"
Requires-Dist: requests-mock>1; extra == "tests"
Dynamic: license-file
